bplsdk/__init__.py
bplsdk/bplprotocol.py
bplsdk/reach.py
bplsdk-0.5.0.dist-info/licenses/LICENSE
bplsdk-0.5.0.dist-info/METADATA
bplsdk-0.5.0.dist-info/WHEEL
bplsdk-0.5.0.dist-info/top_level.txt
bplsdk-0.5.0.dist-info/RECORD
