Metadata-Version: 2.4
Name: bplsdk
Version: 0.5.0
Summary: An SDK for a more ergonomic use of the BPL protocol
Author: Sindre Hansen
Author-email: sindre.hansen@blueye.no
Maintainer: Sindre Hansen
Maintainer-email: sindre.hansen@blueye.no
Requires-Python: >=3.11,<4.0
License-File: LICENSE
Requires-Dist: cobs<2.0.0,>=1.1.4
Requires-Dist: crcmod<2.0,>=1.7
Requires-Dist: pyserial<4.0,>=3.4
Dynamic: author
Dynamic: author-email
Dynamic: license-file
Dynamic: maintainer
Dynamic: maintainer-email
Dynamic: requires-dist
Dynamic: requires-python
Dynamic: summary
